Metadata-Version: 2.4
Name: mcp-youtube-extractor
Version: 0.2.1
Summary: A Model Context Protocol (MCP) server for YouTube operations
License-File: LICENSE
Requires-Python: >=3.10
Requires-Dist: google-api-python-client>=2.172.0
Requires-Dist: mcp>=1.6.0
Requires-Dist: youtube-transcript-api>=1.1.0
